{
  "openapi": "3.0.1",
  "info": {
    "title": "BaristaShop.Catalog",
    "version": "1.0"
  },
  "paths": {
    "/api/AboutUs": {
      "get": {
        "tags": [
          "AboutUs"
        ],
        "responses": {
          "200": {
            "description": "OK"
          }
        }
      },
      "post": {
        "tags": [
          "AboutUs"
        ],
        "requestBody": {
          "content": {
            "application/json": {
              "schema": {
                "$ref": "#/components/schemas/CreateAboutUsDto"
              }
            },
            "text/json": {
              "schema": {
                "$ref": "#/components/schemas/CreateAboutUsDto"
              }
            },
            "application/*+json": {
              "schema": {
                "$ref": "#/components/schemas/CreateAboutUsDto"
              }
            }
          }
        },
        "responses": {
          "200": {
            "description": "OK"
          }
        }
      },
      "put": {
        "tags": [
          "AboutUs"
        ],
        "requestBody": {
          "content": {
            "application/json": {
              "schema": {
                "$ref": "#/components/schemas/UpdateAboutUsDto"
              }
            },
            "text/json": {
              "schema": {
                "$ref": "#/components/schemas/UpdateAboutUsDto"
              }
            },
            "application/*+json": {
              "schema": {
                "$ref": "#/components/schemas/UpdateAboutUsDto"
              }
            }
          }
        },
        "responses": {
          "200": {
            "description": "OK"
          }
        }
      }
    },
    "/api/Categories": {
      "get": {
        "tags": [
          "Categories"
        ],
        "responses": {
          "200": {
            "description": "OK"
          }
        }
      },
      "post": {
        "tags": [
          "Categories"
        ],
        "requestBody": {
          "content": {
            "application/json": {
              "schema": {
                "$ref": "#/components/schemas/CreateCategoryDto"
              }
            },
            "text/json": {
              "schema": {
                "$ref": "#/components/schemas/CreateCategoryDto"
              }
            },
            "application/*+json": {
              "schema": {
                "$ref": "#/components/schemas/CreateCategoryDto"
              }
            }
          }
        },
        "responses": {
          "200": {
            "description": "OK"
          }
        }
      },
      "delete": {
        "tags": [
          "Categories"
        ],
        "parameters": [
          {
            "name": "id",
            "in": "query",
            "schema": {
              "type": "string"
            }
          }
        ],
        "responses": {
          "200": {
            "description": "OK"
          }
        }
      },
      "put": {
        "tags": [
          "Categories"
        ],
        "requestBody": {
          "content": {
            "application/json": {
              "schema": {
                "$ref": "#/components/schemas/UpdateCategoryDto"
              }
            },
            "text/json": {
              "schema": {
                "$ref": "#/components/schemas/UpdateCategoryDto"
              }
            },
            "application/*+json": {
              "schema": {
                "$ref": "#/components/schemas/UpdateCategoryDto"
              }
            }
          }
        },
        "responses": {
          "200": {
            "description": "OK"
          }
        }
      }
    },
    "/api/Categories/{id}": {
      "get": {
        "tags": [
          "Categories"
        ],
        "parameters": [
          {
            "name": "id",
            "in": "path",
            "required": true,
            "schema": {
              "type": "string"
            }
          }
        ],
        "responses": {
          "200": {
            "description": "OK"
          }
        }
      }
    },
    "/api/FeatureSliders": {
      "get": {
        "tags": [
          "FeatureSliders"
        ],
        "responses": {
          "200": {
            "description": "OK"
          }
        }
      },
      "post": {
        "tags": [
          "FeatureSliders"
        ],
        "requestBody": {
          "content": {
            "application/json": {
              "schema": {
                "$ref": "#/components/schemas/CreateFeatureSliderDto"
              }
            },
            "text/json": {
              "schema": {
                "$ref": "#/components/schemas/CreateFeatureSliderDto"
              }
            },
            "application/*+json": {
              "schema": {
                "$ref": "#/components/schemas/CreateFeatureSliderDto"
              }
            }
          }
        },
        "responses": {
          "200": {
            "description": "OK"
          }
        }
      },
      "put": {
        "tags": [
          "FeatureSliders"
        ],
        "requestBody": {
          "content": {
            "application/json": {
              "schema": {
                "$ref": "#/components/schemas/UpdateFeatureSliderDto"
              }
            },
            "text/json": {
              "schema": {
                "$ref": "#/components/schemas/UpdateFeatureSliderDto"
              }
            },
            "application/*+json": {
              "schema": {
                "$ref": "#/components/schemas/UpdateFeatureSliderDto"
              }
            }
          }
        },
        "responses": {
          "200": {
            "description": "OK"
          }
        }
      }
    },
    "/api/FeatureSliders/{id}": {
      "get": {
        "tags": [
          "FeatureSliders"
        ],
        "parameters": [
          {
            "name": "id",
            "in": "path",
            "required": true,
            "schema": {
              "type": "string"
            }
          }
        ],
        "responses": {
          "200": {
            "description": "OK"
          }
        }
      },
      "delete": {
        "tags": [
          "FeatureSliders"
        ],
        "parameters": [
          {
            "name": "id",
            "in": "path",
            "required": true,
            "schema": {
              "type": "string"
            }
          }
        ],
        "responses": {
          "200": {
            "description": "OK"
          }
        }
      }
    },
    "/api/ProductDetails": {
      "get": {
        "tags": [
          "ProductDetails"
        ],
        "responses": {
          "200": {
            "description": "OK"
          }
        }
      },
      "post": {
        "tags": [
          "ProductDetails"
        ],
        "requestBody": {
          "content": {
            "application/json": {
              "schema": {
                "$ref": "#/components/schemas/CreateProductDetailDto"
              }
            },
            "text/json": {
              "schema": {
                "$ref": "#/components/schemas/CreateProductDetailDto"
              }
            },
            "application/*+json": {
              "schema": {
                "$ref": "#/components/schemas/CreateProductDetailDto"
              }
            }
          }
        },
        "responses": {
          "200": {
            "description": "OK"
          }
        }
      },
      "delete": {
        "tags": [
          "ProductDetails"
        ],
        "parameters": [
          {
            "name": "id",
            "in": "query",
            "schema": {
              "type": "string"
            }
          }
        ],
        "responses": {
          "200": {
            "description": "OK"
          }
        }
      },
      "put": {
        "tags": [
          "ProductDetails"
        ],
        "requestBody": {
          "content": {
            "application/json": {
              "schema": {
                "$ref": "#/components/schemas/UpdateProductDetailDto"
              }
            },
            "text/json": {
              "schema": {
                "$ref": "#/components/schemas/UpdateProductDetailDto"
              }
            },
            "application/*+json": {
              "schema": {
                "$ref": "#/components/schemas/UpdateProductDetailDto"
              }
            }
          }
        },
        "responses": {
          "200": {
            "description": "OK"
          }
        }
      }
    },
    "/api/ProductDetails/{id}": {
      "get": {
        "tags": [
          "ProductDetails"
        ],
        "parameters": [
          {
            "name": "id",
            "in": "path",
            "required": true,
            "schema": {
              "type": "string"
            }
          }
        ],
        "responses": {
          "200": {
            "description": "OK"
          }
        }
      }
    },
    "/api/ProductDetails/byproduct/{productId}": {
      "get": {
        "tags": [
          "ProductDetails"
        ],
        "parameters": [
          {
            "name": "productId",
            "in": "path",
            "required": true,
            "schema": {
              "type": "string"
            }
          }
        ],
        "responses": {
          "200": {
            "description": "OK"
          }
        }
      }
    },
    "/api/ProductImages": {
      "get": {
        "tags": [
          "ProductImages"
        ],
        "responses": {
          "200": {
            "description": "OK"
          }
        }
      },
      "post": {
        "tags": [
          "ProductImages"
        ],
        "requestBody": {
          "content": {
            "application/json": {
              "schema": {
                "$ref": "#/components/schemas/CreateProductImageDto"
              }
            },
            "text/json": {
              "schema": {
                "$ref": "#/components/schemas/CreateProductImageDto"
              }
            },
            "application/*+json": {
              "schema": {
                "$ref": "#/components/schemas/CreateProductImageDto"
              }
            }
          }
        },
        "responses": {
          "200": {
            "description": "OK"
          }
        }
      },
      "put": {
        "tags": [
          "ProductImages"
        ],
        "requestBody": {
          "content": {
            "application/json": {
              "schema": {
                "$ref": "#/components/schemas/UpdateProductImageDto"
              }
            },
            "text/json": {
              "schema": {
                "$ref": "#/components/schemas/UpdateProductImageDto"
              }
            },
            "application/*+json": {
              "schema": {
                "$ref": "#/components/schemas/UpdateProductImageDto"
              }
            }
          }
        },
        "responses": {
          "200": {
            "description": "OK"
          }
        }
      }
    },
    "/api/ProductImages/{id}": {
      "get": {
        "tags": [
          "ProductImages"
        ],
        "parameters": [
          {
            "name": "id",
            "in": "path",
            "required": true,
            "schema": {
              "type": "string"
            }
          }
        ],
        "responses": {
          "200": {
            "description": "OK"
          }
        }
      },
      "delete": {
        "tags": [
          "ProductImages"
        ],
        "parameters": [
          {
            "name": "id",
            "in": "path",
            "required": true,
            "schema": {
              "type": "string"
            }
          }
        ],
        "responses": {
          "200": {
            "description": "OK"
          }
        }
      }
    },
    "/api/ProductImages/byproduct/{productId}": {
      "get": {
        "tags": [
          "ProductImages"
        ],
        "parameters": [
          {
            "name": "productId",
            "in": "path",
            "required": true,
            "schema": {
              "type": "string"
            }
          }
        ],
        "responses": {
          "200": {
            "description": "OK"
          }
        }
      }
    },
    "/api/ProductItems": {
      "get": {
        "tags": [
          "ProductItems"
        ],
        "responses": {
          "200": {
            "description": "OK"
          }
        }
      },
      "post": {
        "tags": [
          "ProductItems"
        ],
        "requestBody": {
          "content": {
            "application/json": {
              "schema": {
                "$ref": "#/components/schemas/CreateProductItemDto"
              }
            },
            "text/json": {
              "schema": {
                "$ref": "#/components/schemas/CreateProductItemDto"
              }
            },
            "application/*+json": {
              "schema": {
                "$ref": "#/components/schemas/CreateProductItemDto"
              }
            }
          }
        },
        "responses": {
          "200": {
            "description": "OK"
          }
        }
      },
      "put": {
        "tags": [
          "ProductItems"
        ],
        "requestBody": {
          "content": {
            "application/json": {
              "schema": {
                "$ref": "#/components/schemas/UpdateProductItemDto"
              }
            },
            "text/json": {
              "schema": {
                "$ref": "#/components/schemas/UpdateProductItemDto"
              }
            },
            "application/*+json": {
              "schema": {
                "$ref": "#/components/schemas/UpdateProductItemDto"
              }
            }
          }
        },
        "responses": {
          "200": {
            "description": "OK"
          }
        }
      }
    },
    "/api/ProductItems/{id}": {
      "get": {
        "tags": [
          "ProductItems"
        ],
        "parameters": [
          {
            "name": "id",
            "in": "path",
            "required": true,
            "schema": {
              "type": "string"
            }
          }
        ],
        "responses": {
          "200": {
            "description": "OK"
          }
        }
      },
      "delete": {
        "tags": [
          "ProductItems"
        ],
        "parameters": [
          {
            "name": "id",
            "in": "path",
            "required": true,
            "schema": {
              "type": "string"
            }
          }
        ],
        "responses": {
          "200": {
            "description": "OK"
          }
        }
      }
    },
    "/api/ProductItems/byproduct/{productId}": {
      "get": {
        "tags": [
          "ProductItems"
        ],
        "parameters": [
          {
            "name": "productId",
            "in": "path",
            "required": true,
            "schema": {
              "type": "string"
            }
          }
        ],
        "responses": {
          "200": {
            "description": "OK"
          }
        }
      }
    },
    "/api/Products": {
      "get": {
        "tags": [
          "Products"
        ],
        "responses": {
          "200": {
            "description": "OK"
          }
        }
      },
      "post": {
        "tags": [
          "Products"
        ],
        "requestBody": {
          "content": {
            "application/json": {
              "schema": {
                "$ref": "#/components/schemas/CreateProductDto"
              }
            },
            "text/json": {
              "schema": {
                "$ref": "#/components/schemas/CreateProductDto"
              }
            },
            "application/*+json": {
              "schema": {
                "$ref": "#/components/schemas/CreateProductDto"
              }
            }
          }
        },
        "responses": {
          "200": {
            "description": "OK"
          }
        }
      },
      "put": {
        "tags": [
          "Products"
        ],
        "requestBody": {
          "content": {
            "application/json": {
              "schema": {
                "$ref": "#/components/schemas/UpdateProductDto"
              }
            },
            "text/json": {
              "schema": {
                "$ref": "#/components/schemas/UpdateProductDto"
              }
            },
            "application/*+json": {
              "schema": {
                "$ref": "#/components/schemas/UpdateProductDto"
              }
            }
          }
        },
        "responses": {
          "200": {
            "description": "OK"
          }
        }
      }
    },
    "/api/Products/{id}": {
      "get": {
        "tags": [
          "Products"
        ],
        "parameters": [
          {
            "name": "id",
            "in": "path",
            "required": true,
            "schema": {
              "type": "string"
            }
          }
        ],
        "responses": {
          "200": {
            "description": "OK"
          }
        }
      },
      "delete": {
        "tags": [
          "Products"
        ],
        "parameters": [
          {
            "name": "id",
            "in": "path",
            "required": true,
            "schema": {
              "type": "string"
            }
          }
        ],
        "responses": {
          "200": {
            "description": "OK"
          }
        }
      }
    },
    "/api/Products/featured": {
      "get": {
        "tags": [
          "Products"
        ],
        "responses": {
          "200": {
            "description": "OK"
          }
        }
      }
    },
    "/api/ProductVariants": {
      "get": {
        "tags": [
          "ProductVariants"
        ],
        "responses": {
          "200": {
            "description": "OK"
          }
        }
      },
      "post": {
        "tags": [
          "ProductVariants"
        ],
        "requestBody": {
          "content": {
            "application/json": {
              "schema": {
                "$ref": "#/components/schemas/CreateProductVariantDto"
              }
            },
            "text/json": {
              "schema": {
                "$ref": "#/components/schemas/CreateProductVariantDto"
              }
            },
            "application/*+json": {
              "schema": {
                "$ref": "#/components/schemas/CreateProductVariantDto"
              }
            }
          }
        },
        "responses": {
          "200": {
            "description": "OK"
          }
        }
      },
      "put": {
        "tags": [
          "ProductVariants"
        ],
        "requestBody": {
          "content": {
            "application/json": {
              "schema": {
                "$ref": "#/components/schemas/UpdateProductVariantDto"
              }
            },
            "text/json": {
              "schema": {
                "$ref": "#/components/schemas/UpdateProductVariantDto"
              }
            },
            "application/*+json": {
              "schema": {
                "$ref": "#/components/schemas/UpdateProductVariantDto"
              }
            }
          }
        },
        "responses": {
          "200": {
            "description": "OK"
          }
        }
      }
    },
    "/api/ProductVariants/{id}": {
      "get": {
        "tags": [
          "ProductVariants"
        ],
        "parameters": [
          {
            "name": "id",
            "in": "path",
            "required": true,
            "schema": {
              "type": "string"
            }
          }
        ],
        "responses": {
          "200": {
            "description": "OK"
          }
        }
      },
      "delete": {
        "tags": [
          "ProductVariants"
        ],
        "parameters": [
          {
            "name": "id",
            "in": "path",
            "required": true,
            "schema": {
              "type": "string"
            }
          }
        ],
        "responses": {
          "200": {
            "description": "OK"
          }
        }
      }
    },
    "/api/SpecialOffers": {
      "get": {
        "tags": [
          "SpecialOffers"
        ],
        "responses": {
          "200": {
            "description": "OK"
          }
        }
      },
      "post": {
        "tags": [
          "SpecialOffers"
        ],
        "requestBody": {
          "content": {
            "application/json": {
              "schema": {
                "$ref": "#/components/schemas/CreateSpecialOfferDto"
              }
            },
            "text/json": {
              "schema": {
                "$ref": "#/components/schemas/CreateSpecialOfferDto"
              }
            },
            "application/*+json": {
              "schema": {
                "$ref": "#/components/schemas/CreateSpecialOfferDto"
              }
            }
          }
        },
        "responses": {
          "200": {
            "description": "OK"
          }
        }
      },
      "put": {
        "tags": [
          "SpecialOffers"
        ],
        "requestBody": {
          "content": {
            "application/json": {
              "schema": {
                "$ref": "#/components/schemas/UpdateSpecialOfferDto"
              }
            },
            "text/json": {
              "schema": {
                "$ref": "#/components/schemas/UpdateSpecialOfferDto"
              }
            },
            "application/*+json": {
              "schema": {
                "$ref": "#/components/schemas/UpdateSpecialOfferDto"
              }
            }
          }
        },
        "responses": {
          "200": {
            "description": "OK"
          }
        }
      }
    },
    "/api/SpecialOffers/{id}": {
      "get": {
        "tags": [
          "SpecialOffers"
        ],
        "parameters": [
          {
            "name": "id",
            "in": "path",
            "required": true,
            "schema": {
              "type": "string"
            }
          }
        ],
        "responses": {
          "200": {
            "description": "OK"
          }
        }
      },
      "delete": {
        "tags": [
          "SpecialOffers"
        ],
        "parameters": [
          {
            "name": "id",
            "in": "path",
            "required": true,
            "schema": {
              "type": "string"
            }
          }
        ],
        "responses": {
          "200": {
            "description": "OK"
          }
        }
      }
    },
    "/api/Statistics/GetCategoryCount": {
      "get": {
        "tags": [
          "Statistics"
        ],
        "responses": {
          "200": {
            "description": "OK"
          }
        }
      }
    },
    "/api/Statistics/GetProductCount": {
      "get": {
        "tags": [
          "Statistics"
        ],
        "responses": {
          "200": {
            "description": "OK"
          }
        }
      }
    },
    "/api/Statistics/GetProductAvgPrice": {
      "get": {
        "tags": [
          "Statistics"
        ],
        "responses": {
          "200": {
            "description": "OK"
          }
        }
      }
    },
    "/api/Statistics/GetMaxPriceProductName": {
      "get": {
        "tags": [
          "Statistics"
        ],
        "responses": {
          "200": {
            "description": "OK"
          }
        }
      }
    },
    "/api/Statistics/GetMinPriceProductName": {
      "get": {
        "tags": [
          "Statistics"
        ],
        "responses": {
          "200": {
            "description": "OK"
          }
        }
      }
    },
    "/api/VariantOptions": {
      "get": {
        "tags": [
          "VariantOptions"
        ],
        "responses": {
          "200": {
            "description": "OK"
          }
        }
      },
      "post": {
        "tags": [
          "VariantOptions"
        ],
        "requestBody": {
          "content": {
            "application/json": {
              "schema": {
                "$ref": "#/components/schemas/CreateVariantOptionDto"
              }
            },
            "text/json": {
              "schema": {
                "$ref": "#/components/schemas/CreateVariantOptionDto"
              }
            },
            "application/*+json": {
              "schema": {
                "$ref": "#/components/schemas/CreateVariantOptionDto"
              }
            }
          }
        },
        "responses": {
          "200": {
            "description": "OK"
          }
        }
      },
      "delete": {
        "tags": [
          "VariantOptions"
        ],
        "parameters": [
          {
            "name": "id",
            "in": "query",
            "schema": {
              "type": "string"
            }
          }
        ],
        "responses": {
          "200": {
            "description": "OK"
          }
        }
      },
      "put": {
        "tags": [
          "VariantOptions"
        ],
        "requestBody": {
          "content": {
            "application/json": {
              "schema": {
                "$ref": "#/components/schemas/UpdateVariantOptionDto"
              }
            },
            "text/json": {
              "schema": {
                "$ref": "#/components/schemas/UpdateVariantOptionDto"
              }
            },
            "application/*+json": {
              "schema": {
                "$ref": "#/components/schemas/UpdateVariantOptionDto"
              }
            }
          }
        },
        "responses": {
          "200": {
            "description": "OK"
          }
        }
      }
    },
    "/api/VariantOptions/{id}": {
      "get": {
        "tags": [
          "VariantOptions"
        ],
        "parameters": [
          {
            "name": "id",
            "in": "path",
            "required": true,
            "schema": {
              "type": "string"
            }
          }
        ],
        "responses": {
          "200": {
            "description": "OK"
          }
        }
      }
    },
    "/api/Variants": {
      "get": {
        "tags": [
          "Variants"
        ],
        "responses": {
          "200": {
            "description": "OK"
          }
        }
      },
      "post": {
        "tags": [
          "Variants"
        ],
        "requestBody": {
          "content": {
            "application/json": {
              "schema": {
                "$ref": "#/components/schemas/CreateVariantDto"
              }
            },
            "text/json": {
              "schema": {
                "$ref": "#/components/schemas/CreateVariantDto"
              }
            },
            "application/*+json": {
              "schema": {
                "$ref": "#/components/schemas/CreateVariantDto"
              }
            }
          }
        },
        "responses": {
          "200": {
            "description": "OK"
          }
        }
      },
      "delete": {
        "tags": [
          "Variants"
        ],
        "parameters": [
          {
            "name": "id",
            "in": "query",
            "schema": {
              "type": "string"
            }
          }
        ],
        "responses": {
          "200": {
            "description": "OK"
          }
        }
      },
      "put": {
        "tags": [
          "Variants"
        ],
        "requestBody": {
          "content": {
            "application/json": {
              "schema": {
                "$ref": "#/components/schemas/UpdateVariantDto"
              }
            },
            "text/json": {
              "schema": {
                "$ref": "#/components/schemas/UpdateVariantDto"
              }
            },
            "application/*+json": {
              "schema": {
                "$ref": "#/components/schemas/UpdateVariantDto"
              }
            }
          }
        },
        "responses": {
          "200": {
            "description": "OK"
          }
        }
      }
    },
    "/api/Variants/{id}": {
      "get": {
        "tags": [
          "Variants"
        ],
        "parameters": [
          {
            "name": "id",
            "in": "path",
            "required": true,
            "schema": {
              "type": "string"
            }
          }
        ],
        "responses": {
          "200": {
            "description": "OK"
          }
        }
      }
    }
  },
  "components": {
    "schemas": {
      "CreateAboutUsDto": {
        "type": "object",
        "properties": {
          "aboutInfo": {
            "type": "string",
            "nullable": true
          },
          "aboutEmail": {
            "type": "string",
            "nullable": true
          },
          "aboutPhone": {
            "type": "string",
            "nullable": true
          }
        },
        "additionalProperties": false
      },
      "CreateCategoryDto": {
        "type": "object",
        "properties": {
          "categoryName": {
            "type": "string",
            "nullable": true
          },
          "categoryImage": {
            "type": "string",
            "nullable": true
          }
        },
        "additionalProperties": false
      },
      "CreateFeatureSliderDto": {
        "type": "object",
        "properties": {
          "featureSliderTitle": {
            "type": "string",
            "nullable": true
          },
          "featureSliderDescription": {
            "type": "string",
            "nullable": true
          },
          "featureSliderImage": {
            "type": "string",
            "nullable": true
          }
        },
        "additionalProperties": false
      },
      "CreateProductDetailDto": {
        "type": "object",
        "properties": {
          "productDescription": {
            "type": "string",
            "nullable": true
          },
          "productInfo": {
            "type": "string",
            "nullable": true
          },
          "productId": {
            "type": "string",
            "nullable": true
          }
        },
        "additionalProperties": false
      },
      "CreateProductDto": {
        "type": "object",
        "properties": {
          "productName": {
            "type": "string",
            "nullable": true
          },
          "productIsActive": {
            "type": "boolean"
          },
          "categoryId": {
            "type": "string",
            "nullable": true
          }
        },
        "additionalProperties": false
      },
      "CreateProductImageDto": {
        "type": "object",
        "properties": {
          "image1": {
            "type": "string",
            "nullable": true
          },
          "image2": {
            "type": "string",
            "nullable": true
          },
          "image3": {
            "type": "string",
            "nullable": true
          },
          "image4": {
            "type": "string",
            "nullable": true
          },
          "image5": {
            "type": "string",
            "nullable": true
          },
          "image6": {
            "type": "string",
            "nullable": true
          },
          "productId": {
            "type": "string",
            "nullable": true
          }
        },
        "additionalProperties": false
      },
      "CreateProductItemDto": {
        "type": "object",
        "properties": {
          "productId": {
            "type": "string",
            "nullable": true
          },
          "sku": {
            "type": "string",
            "nullable": true
          },
          "productStock": {
            "type": "integer",
            "format": "int32"
          },
          "productPrice": {
            "type": "number",
            "format": "double"
          },
          "productPriceWithSale": {
            "type": "number",
            "format": "double"
          }
        },
        "additionalProperties": false
      },
      "CreateProductVariantDto": {
        "type": "object",
        "properties": {
          "productItemId": {
            "type": "string",
            "nullable": true
          },
          "variantOptionId": {
            "type": "string",
            "nullable": true
          }
        },
        "additionalProperties": false
      },
      "CreateSpecialOfferDto": {
        "type": "object",
        "properties": {
          "specialOfferTitle": {
            "type": "string",
            "nullable": true
          },
          "specialOfferSubTitle": {
            "type": "string",
            "nullable": true
          },
          "specialOfferImage": {
            "type": "string",
            "nullable": true
          }
        },
        "additionalProperties": false
      },
      "CreateVariantDto": {
        "type": "object",
        "properties": {
          "variantName": {
            "type": "string",
            "nullable": true
          },
          "categoryId": {
            "type": "string",
            "nullable": true
          }
        },
        "additionalProperties": false
      },
      "CreateVariantOptionDto": {
        "type": "object",
        "properties": {
          "variantOptionValue": {
            "type": "string",
            "nullable": true
          },
          "variantId": {
            "type": "string",
            "nullable": true
          }
        },
        "additionalProperties": false
      },
      "UpdateAboutUsDto": {
        "type": "object",
        "properties": {
          "aboutId": {
            "type": "string",
            "nullable": true
          },
          "aboutInfo": {
            "type": "string",
            "nullable": true
          },
          "aboutEmail": {
            "type": "string",
            "nullable": true
          },
          "aboutPhone": {
            "type": "string",
            "nullable": true
          }
        },
        "additionalProperties": false
      },
      "UpdateCategoryDto": {
        "type": "object",
        "properties": {
          "categoryId": {
            "type": "string",
            "nullable": true
          },
          "categoryName": {
            "type": "string",
            "nullable": true
          },
          "categoryImage": {
            "type": "string",
            "nullable": true
          }
        },
        "additionalProperties": false
      },
      "UpdateFeatureSliderDto": {
        "type": "object",
        "properties": {
          "featureSliderId": {
            "type": "string",
            "nullable": true
          },
          "featureSliderTitle": {
            "type": "string",
            "nullable": true
          },
          "featureSliderDescription": {
            "type": "string",
            "nullable": true
          },
          "featureSliderImage": {
            "type": "string",
            "nullable": true
          }
        },
        "additionalProperties": false
      },
      "UpdateProductDetailDto": {
        "type": "object",
        "properties": {
          "productDetailId": {
            "type": "string",
            "nullable": true
          },
          "productDescription": {
            "type": "string",
            "nullable": true
          },
          "productInfo": {
            "type": "string",
            "nullable": true
          },
          "productId": {
            "type": "string",
            "nullable": true
          }
        },
        "additionalProperties": false
      },
      "UpdateProductDto": {
        "type": "object",
        "properties": {
          "productId": {
            "type": "string",
            "nullable": true
          },
          "productName": {
            "type": "string",
            "nullable": true
          },
          "productIsActive": {
            "type": "boolean"
          },
          "categoryId": {
            "type": "string",
            "nullable": true
          }
        },
        "additionalProperties": false
      },
      "UpdateProductImageDto": {
        "type": "object",
        "properties": {
          "productImageId": {
            "type": "string",
            "nullable": true
          },
          "image1": {
            "type": "string",
            "nullable": true
          },
          "image2": {
            "type": "string",
            "nullable": true
          },
          "image3": {
            "type": "string",
            "nullable": true
          },
          "image4": {
            "type": "string",
            "nullable": true
          },
          "image5": {
            "type": "string",
            "nullable": true
          },
          "image6": {
            "type": "string",
            "nullable": true
          },
          "productId": {
            "type": "string",
            "nullable": true
          }
        },
        "additionalProperties": false
      },
      "UpdateProductItemDto": {
        "type": "object",
        "properties": {
          "productItemId": {
            "type": "string",
            "nullable": true
          },
          "productId": {
            "type": "string",
            "nullable": true
          },
          "sku": {
            "type": "string",
            "nullable": true
          },
          "productStock": {
            "type": "integer",
            "format": "int32"
          },
          "productPrice": {
            "type": "number",
            "format": "double"
          },
          "productPriceWithSale": {
            "type": "number",
            "format": "double"
          }
        },
        "additionalProperties": false
      },
      "UpdateProductVariantDto": {
        "type": "object",
        "properties": {
          "productVariantId": {
            "type": "string",
            "nullable": true
          },
          "productItemId": {
            "type": "string",
            "nullable": true
          },
          "variantOptionId": {
            "type": "string",
            "nullable": true
          }
        },
        "additionalProperties": false
      },
      "UpdateSpecialOfferDto": {
        "type": "object",
        "properties": {
          "specialOfferId": {
            "type": "string",
            "nullable": true
          },
          "specialOfferTitle": {
            "type": "string",
            "nullable": true
          },
          "specialOfferSubTitle": {
            "type": "string",
            "nullable": true
          },
          "specialOfferImage": {
            "type": "string",
            "nullable": true
          }
        },
        "additionalProperties": false
      },
      "UpdateVariantDto": {
        "type": "object",
        "properties": {
          "variantId": {
            "type": "string",
            "nullable": true
          },
          "variantName": {
            "type": "string",
            "nullable": true
          },
          "categoryId": {
            "type": "string",
            "nullable": true
          }
        },
        "additionalProperties": false
      },
      "UpdateVariantOptionDto": {
        "type": "object",
        "properties": {
          "variantOptionId": {
            "type": "string",
            "nullable": true
          },
          "variantOptionValue": {
            "type": "string",
            "nullable": true
          },
          "variantId": {
            "type": "string",
            "nullable": true
          }
        },
        "additionalProperties": false
      }
    }
  }
}